taiga_contrib_kerberos_auth/apps.py
taiga_contrib_kerberos_auth/connector.py
taiga_contrib_kerberos_auth/services.py
taiga_contrib_kerberos_auth/__init__.py
taiga_contrib_kerberos_auth-0.1.9.dist-info/WHEEL
taiga_contrib_kerberos_auth-0.1.9.dist-info/DESCRIPTION.rst
taiga_contrib_kerberos_auth-0.1.9.dist-info/RECORD
taiga_contrib_kerberos_auth-0.1.9.dist-info/top_level.txt
taiga_contrib_kerberos_auth-0.1.9.dist-info/METADATA
taiga_contrib_kerberos_auth-0.1.9.dist-info/metadata.json
